README.md
setup.py
common/DBHolder.py
common/TimeEntry.py
common/TimeSheet.py
common/__init__.py
common/prompt_checking.py
tests/__init__.py
tests/test_TimeEntry.py
tests/test_TimeSheet.py
tests/test_prompt_checking.py
timmy/__init__.py
timmy/main.py
timmytimesheet.egg-info/PKG-INFO
timmytimesheet.egg-info/SOURCES.txt
timmytimesheet.egg-info/dependency_links.txt
timmytimesheet.egg-info/entry_points.txt
timmytimesheet.egg-info/requires.txt
timmytimesheet.egg-info/top_level.txt