Metadata-Version: 2.1
Name: timmytimesheet
Version: 0.1.5.3
Summary: a basic timesheeting cli
Author: jumper385 (Henry Chen)
Keywords: timesheeting
Classifier: Programming Language :: Python :: 3
Classifier: License :: OSI Approved :: MIT License
Classifier: Operating System :: OS Independent
Requires-Dist: typer[all]
Requires-Dist: python-dateutil
